tti/__init__.py
tti/indicators/__init__.py
tti/indicators/_accumulation_distribution_line.py
tti/indicators/_average_true_range.py
tti/indicators/_bollinger_bands.py
tti/indicators/_chaikin_money_flow.py
tti/indicators/_chaikin_oscillator.py
tti/indicators/_chande_momentum_oscillator.py
tti/indicators/_commodity_channel_index.py
tti/indicators/_detrended_price_oscillator.py
tti/indicators/_directional_movement_index.py
tti/indicators/_double_exponential_moving_average.py
tti/indicators/_ease_of_movement.py
tti/indicators/_envelopes.py
tti/indicators/_fibonacci_retracement.py
tti/indicators/_forecast_oscillator.py
tti/indicators/_ichimoku_cloud.py
tti/indicators/_intraday_movement_index.py
tti/indicators/_klinger_oscillator.py
tti/indicators/_linear_regression_indicator.py
tti/indicators/_linear_regression_slope.py
tti/indicators/_market_facilitation_index.py
tti/indicators/_mass_index.py
tti/indicators/_median_price.py
tti/indicators/_momentum.py
tti/indicators/_moving_average.py
tti/indicators/_moving_average_convergence_divergence.py
tti/indicators/_negative_volume_index.py
tti/indicators/_on_balance_volume.py
tti/indicators/_parabolic_sar.py
tti/indicators/_performance.py
tti/indicators/_positive_volume_index.py
tti/indicators/_price_and_volume_trend.py
tti/indicators/_price_channel.py
tti/indicators/_price_oscillator.py
tti/indicators/_price_rate_of_change.py
tti/indicators/_projection_bands.py
tti/indicators/_projection_oscillator.py
tti/indicators/_qstick.py
tti/indicators/_range_indicator.py
tti/indicators/_relative_momentum_index.py
tti/indicators/_relative_strength_index.py
tti/indicators/_relative_volatility_index.py
tti/indicators/_standard_deviation.py
tti/indicators/_stochastic_momentum_index.py
tti/indicators/_stochastic_oscillator.py
tti/indicators/_swing_index.py
tti/indicators/_technical_indicator.py
tti/indicators/_time_series_forecast.py
tti/indicators/_triple_exponential_moving_average.py
tti/indicators/_typical_price.py
tti-0.2.2.dist-info/LICENSE
tti-0.2.2.dist-info/METADATA
tti-0.2.2.dist-info/WHEEL
tti-0.2.2.dist-info/top_level.txt
tti-0.2.2.dist-info/RECORD
