Metadata-Version: 2.1
Name: tti
Version: 0.2.2
Summary: Trading Technical Indicators, python library. Where Traditional Technical Analysis and AI are met.
Home-page: https://www.trading-technical-indicators.org/
Author: Vasileios Saveris
Author-email: vsaveris@gmail.com
License: MIT
Download-URL: https://pypi.org/project/tti/#files
Project-URL: Bug Tracker, https://github.com/vsaveris/trading-technical-indicators/issues
Project-URL: Documentation, https://www.trading-technical-indicators.org/api-docs
Project-URL: Source Code, https://github.com/vsaveris/trading-technical-indicators
Platform: UNKNOWN
Classifier: Development Status :: 5 - Production/Stable
Classifier: Intended Audience :: Science/Research
Classifier: Intended Audience :: Developers
Classifier: License :: OSI Approved :: MIT License
Classifier: Operating System :: Microsoft :: Windows
Classifier: Operating System :: POSIX
Classifier: Operating System :: Unix
Classifier: Operating System :: MacOS
Classifier: Programming Language :: Python
Classifier: Programming Language :: Python :: 3.8
Classifier: Programming Language :: Python :: 3.9
Classifier: Topic :: Software Development
Classifier: Topic :: Scientific/Engineering
Classifier: Topic :: Software Development :: Libraries :: Python Modules
Classifier: Topic :: Scientific/Engineering :: Artificial Intelligence
Classifier: Topic :: Office/Business :: Financial
Requires-Python: >=3.8
Requires-Dist: pandas (>=1.2.0)
Requires-Dist: matplotlib (>=3.3.3)
Requires-Dist: numpy (>=1.19.4)
Requires-Dist: statsmodels (>=0.12.1)
